object_cache/__init__.py
object_cache-0.1.6.dist-info/LICENSE
object_cache-0.1.6.dist-info/WHEEL
object_cache-0.1.6.dist-info/METADATA
object_cache-0.1.6.dist-info/RECORD
