Metadata-Version: 2.1
Name: object-cache
Version: 0.1.6
Summary: This module caches the result of function.
Home-page: https://github.com/u-masao/object-cache
Author: u-masao
Author-email: 4973920+u-masao@users.noreply.github.com
Requires-Python: >=3.8,<4.0
Classifier: Programming Language :: Python :: 3
Classifier: Programming Language :: Python :: 3.8
Requires-Dist: cloudpickle (>=1.6.0,<2.0.0)
Project-URL: Repository, https://github.com/u-masao/object-cache
